sayou/rag/core/exceptions.py
sayou/rag/interfaces/base_router.py
sayou/rag/interfaces/base_tracer.py
sayou/rag/interfaces/base_transformer.py
sayou/rag/pipeline/advanced.py
sayou/rag/pipeline/basic.py
sayou/rag/pipeline/pipeline.py
sayou/rag/pipeline/rag_stage.py
sayou/rag/router/sft_router.py
sayou/rag/tracer/kg_tracer.py
sayou/rag/transformer/hyde_transformer.py
sayou_rag-0.0.6.dist-info/METADATA
sayou_rag-0.0.6.dist-info/WHEEL
sayou_rag-0.0.6.dist-info/RECORD
